alibabacloud_ailab_vision_public20210709/__init__.py
alibabacloud_ailab_vision_public20210709/client.py
alibabacloud_ailab_vision_public20210709/models.py
alibabacloud_ailab_vision_public20210709-1.0.9.dist-info/LICENSE
alibabacloud_ailab_vision_public20210709-1.0.9.dist-info/METADATA
alibabacloud_ailab_vision_public20210709-1.0.9.dist-info/WHEEL
alibabacloud_ailab_vision_public20210709-1.0.9.dist-info/top_level.txt
alibabacloud_ailab_vision_public20210709-1.0.9.dist-info/RECORD
